guspy/__init__.py
guspy/access.py
guspy/filters.py
guspy/parsers.py
guspy-2.13.data/data/resources/cli.json
guspy-2.13.data/data/resources/objects.json
guspy-2.13.dist-info/LICENSE
guspy-2.13.dist-info/METADATA
guspy-2.13.dist-info/WHEEL
guspy-2.13.dist-info/top_level.txt
guspy-2.13.dist-info/RECORD
