Metadata-Version: 2.1
Name: guspy
Version: 2.13
Summary: Simple Python Wrapper for common GUS Objects
Home-page: https://github.com/cherdon/guspy
Author: Liew Cher Don
Author-email: liewcherdon@gmail.com
Classifier: Programming Language :: Python :: 3.8
Classifier: License :: OSI Approved :: MIT License
Classifier: Operating System :: OS Independent
License-File: LICENSE
